{
  "based_on_period": 115000133,
  "based_on_date": "2026-06-01",
  "target_period": 115000134,
  "target_expected_date": "2026-06-02",
  "top5": [
    7,
    18,
    22,
    27,
    20
  ],
  "top10": [
    7,
    18,
    22,
    27,
    20,
    16,
    23,
    29,
    28,
    9
  ],
  "top15": [
    7,
    18,
    22,
    27,
    20,
    16,
    23,
    29,
    28,
    9,
    35,
    17,
    32,
    5,
    34
  ],
  "unlikely_packs": {
    "five_miss": {
      "name": "5不中暫避",
      "numbers": [
        1,
        3,
        15,
        31,
        37
      ],
      "target": "不中",
      "hit_goal": 0,
      "confidence_index": 97.9,
      "avg_avoid_score": 0.9766,
      "min_avoid_score": 0.9619,
      "source": "historical_backfill_from_saved_candidates",
      "rule": "使用當時已保存候選排序的最低分號碼回填，避免使用未來資料。"
    },
    "ten_miss": {
      "name": "10不中暫避",
      "numbers": [
        1,
        3,
        4,
        11,
        12,
        15,
        21,
        31,
        36,
        37
      ],
      "target": "不中",
      "hit_goal": 0,
      "confidence_index": 97.1,
      "avg_avoid_score": 0.9604,
      "min_avoid_score": 0.9264,
      "source": "historical_backfill_from_saved_candidates",
      "rule": "使用當時已保存候選排序的最低分號碼回填，避免使用未來資料。"
    },
    "fifteen_miss": {
      "name": "15不中暫避",
      "numbers": [
        1,
        2,
        3,
        4,
        6,
        8,
        11,
        12,
        15,
        21,
        25,
        30,
        31,
        36,
        37
      ],
      "target": "不中",
      "hit_goal": 0,
      "confidence_index": 95.3,
      "avg_avoid_score": 0.9239,
      "min_avoid_score": 0.6941,
      "source": "historical_backfill_from_saved_candidates",
      "rule": "使用當時已保存候選排序的最低分號碼回填，避免使用未來資料。"
    }
  },
  "actual_period": 115000134,
  "actual_date": "2026-06-02",
  "actual_numbers": [
    7,
    12,
    22,
    26,
    30
  ],
  "top5_hits": 2,
  "top10_hits": 2,
  "top15_hits": 2,
  "top10_hit_numbers": [
    7,
    22
  ],
  "strong_pack_hits": {
    "strong_single": {
      "name": "最強單支",
      "hit_goal": 1,
      "numbers": [
        7
      ],
      "hits": 1,
      "passed": true
    },
    "two_hit_one": {
      "name": "最強2中1",
      "hit_goal": 1,
      "numbers": [
        7,
        18
      ],
      "hits": 1,
      "passed": true
    },
    "three_hit_one": {
      "name": "最強3中1",
      "hit_goal": 1,
      "numbers": [
        7,
        18,
        22
      ],
      "hits": 2,
      "passed": true
    },
    "five_hit_two": {
      "name": "最強5中2",
      "hit_goal": 2,
      "numbers": [
        7,
        18,
        20,
        22,
        27
      ],
      "hits": 2,
      "passed": true
    },
    "nine_hit_three": {
      "name": "最強9中3",
      "hit_goal": 3,
      "numbers": [
        7,
        9,
        16,
        18,
        20,
        22,
        23,
        27,
        35
      ],
      "hits": 2,
      "passed": false
    }
  },
  "unlikely_pack_hits": {
    "five_miss": {
      "name": "5不中暫避",
      "numbers": [
        1,
        3,
        15,
        31,
        37
      ],
      "target": "不中",
      "hit_goal": 0,
      "accidental_hits": 0,
      "hit_numbers": [],
      "avoided_numbers": [
        1,
        3,
        15,
        31,
        37
      ],
      "passed": true,
      "confidence_index": 97.9,
      "avg_avoid_score": 0.9766,
      "min_avoid_score": 0.9619
    },
    "ten_miss": {
      "name": "10不中暫避",
      "numbers": [
        1,
        3,
        4,
        11,
        12,
        15,
        21,
        31,
        36,
        37
      ],
      "target": "不中",
      "hit_goal": 0,
      "accidental_hits": 1,
      "hit_numbers": [
        12
      ],
      "avoided_numbers": [
        1,
        3,
        4,
        11,
        15,
        21,
        31,
        36,
        37
      ],
      "passed": false,
      "confidence_index": 97.1,
      "avg_avoid_score": 0.9604,
      "min_avoid_score": 0.9264
    },
    "fifteen_miss": {
      "name": "15不中暫避",
      "numbers": [
        1,
        2,
        3,
        4,
        6,
        8,
        11,
        12,
        15,
        21,
        25,
        30,
        31,
        36,
        37
      ],
      "target": "不中",
      "hit_goal": 0,
      "accidental_hits": 2,
      "hit_numbers": [
        12,
        30
      ],
      "avoided_numbers": [
        1,
        2,
        3,
        4,
        6,
        8,
        11,
        15,
        21,
        25,
        31,
        36,
        37
      ],
      "passed": false,
      "confidence_index": 95.3,
      "avg_avoid_score": 0.9239,
      "min_avoid_score": 0.6941
    }
  },
  "status": "settled",
  "created_at": "2026-06-02T12:33:52",
  "settled_at": "2026-06-03T08:40:47",
  "snapshot_count": 0
}