{
    "cleaned_at":  "2026-06-25T07:00:09",
    "root":  "C:\\Users\\MSI\\Documents\\Codex\\539PredictionSystem",
    "removed":  [
                    "__pycache__",
                    "TW539預測系統_20260617_第01版_一鍵版",
                    "TW539預測系統_20260617_第01版_正式封包",
                    "TW539預測系統_20260617_第02版_一鍵版",
                    "TW539預測系統_20260617_第03版_一鍵版",
                    "TW539預測系統_20260617_第04版_一鍵版",
                    "TW539預測系統_20260618_第05版_一鍵版",
                    "TW539預測系統_20260618_第06版_一鍵版",
                    "TW539預測系統_20260618_第07版_一鍵版",
                    "TW539預測系統_20260618_第08版_一鍵版",
                    "TW539預測系統_20260618_第09版_一鍵版",
                    "TW539預測系統_20260618_第10版_一鍵版",
                    "TW539預測系統_20260618_第11版_一鍵版",
                    "TW539預測系統_20260618_第12版_一鍵版",
                    "TW539預測系統_20260618_第13版_一鍵版",
                    "TW539預測系統_20260618_第14版_一鍵版",
                    "TW539預測系統_20260618_第15版_一鍵版",
                    "TW539預測系統_20260618_第16版_一鍵版",
                    "TW539預測系統_20260618_第17版_一鍵版",
                    "TW539預測系統_20260622_第01版_一鍵版",
                    "TW539預測系統_20260622_第02版_一鍵版",
                    "TW539預測系統_20260622_第03版_一鍵版",
                    "TW539預測系統_20260622_第04版_一鍵版",
                    "TW539預測系統_20260622_第05版_一鍵版",
                    "TW539預測系統_20260623_第01版_一鍵版",
                    "TW539預測系統_20260623_第02版_一鍵版",
                    "TW539預測系統_20260624_第01版_一鍵版",
                    "TW539預測系統_20260624_第02版_一鍵版",
                    "TW539預測系統_20260624_第03版_一鍵版",
                    "TW539預測系統_20260624_第04版_一鍵版",
                    "TW539預測系統_20260624_第05版_一鍵版",
                    "TW539預測系統_20260624_第06版_一鍵版",
                    "TW539預測系統_20260624_第07版_一鍵版",
                    "TW539預測系統_20260624_第08版_一鍵版",
                    "TW539預測系統_20260624_第09版_一鍵版",
                    "TW539預測系統_20260617_第01版.zip",
                    "TW539預測系統_20260617_第01版_一鍵版.zip",
                    "TW539預測系統_20260617_第02版_一鍵版.zip",
                    "TW539預測系統_20260617_第03版_一鍵版.zip",
                    "TW539預測系統_20260617_第04版_一鍵版.zip",
                    "TW539預測系統_20260618_第05版_一鍵版.zip",
                    "TW539預測系統_20260618_第06版_一鍵版.zip",
                    "TW539預測系統_20260618_第07版_一鍵版.zip",
                    "TW539預測系統_20260618_第08版_一鍵版.zip",
                    "TW539預測系統_20260618_第09版_一鍵版.zip",
                    "TW539預測系統_20260618_第10版_一鍵版.zip",
                    "TW539預測系統_20260618_第11版_一鍵版.zip",
                    "TW539預測系統_20260618_第12版_一鍵版.zip",
                    "TW539預測系統_20260618_第13版_一鍵版.zip",
                    "TW539預測系統_20260618_第14版_一鍵版.zip",
                    "TW539預測系統_20260618_第15版_一鍵版.zip",
                    "TW539預測系統_20260618_第16版_一鍵版.zip",
                    "TW539預測系統_20260618_第17版_一鍵版.zip",
                    "TW539預測系統_20260622_第01版_一鍵版.zip",
                    "TW539預測系統_20260622_第02版_一鍵版.zip",
                    "TW539預測系統_20260622_第03版_一鍵版.zip",
                    "TW539預測系統_20260622_第04版_一鍵版.zip",
                    "TW539預測系統_20260622_第05版_一鍵版.zip",
                    "TW539預測系統_20260623_第01版_一鍵版.zip",
                    "TW539預測系統_20260623_第02版_一鍵版.zip",
                    "TW539預測系統_20260624_第01版_一鍵版.zip",
                    "TW539預測系統_20260624_第02版_一鍵版.zip",
                    "TW539預測系統_20260624_第03版_一鍵版.zip",
                    "TW539預測系統_20260624_第04版_一鍵版.zip",
                    "TW539預測系統_20260624_第05版_一鍵版.zip",
                    "TW539預測系統_20260624_第06版_一鍵版.zip",
                    "TW539預測系統_20260624_第07版_一鍵版.zip",
                    "TW539預測系統_20260624_第08版_一鍵版.zip",
                    "TW539預測系統_20260624_第09版_一鍵版.zip"
                ],
    "skipped":  [

                ],
    "kept_single_launcher":  "539一鍵全自動啟動.bat",
    "kept_release_base":  "TW539預測系統_20260624_第10版_一鍵版",
    "status":  "ok"
}
